quantlab/__init__.py
quantlab/py.typed
quantlab/analysis/__init__.py
quantlab/analysis/metrics.py
quantlab/core/__init__.py
quantlab/core/engine.py
quantlab/core/evaluator.py
quantlab/core/validator.py
quantlab/data/__init__.py
quantlab/data/loader.py
quantlab/market/__init__.py
quantlab/market/india/__init__.py
quantlab/market/india/charges.py
quantlab/reporting/__init__.py
quantlab/reporting/console.py
quantlab/strategy/__init__.py
quantlab/strategy/base.py
quantlab/utils/__init__.py
quantlab/utils/exceptions.py
quantlab/utils/types.py
quantplay_lab-0.1.0.dist-info/METADATA
quantplay_lab-0.1.0.dist-info/WHEEL
quantplay_lab-0.1.0.dist-info/top_level.txt
quantplay_lab-0.1.0.dist-info/RECORD
