Metadata-Version: 2.1
Name: quantplay-lab
Version: 0.1.0
Summary: High-performance backtesting engine for algorithmic trading with focus on Indian markets
Home-page: https://github.com/yourusername/quantlab
Author: Your Name
Author-email: your.email@example.com
License: MIT
Classifier: Development Status :: 3 - Alpha
Classifier: Intended Audience :: Financial and Insurance Industry
Classifier: License :: OSI Approved :: MIT License
Classifier: Programming Language :: Python :: 3
Classifier: Programming Language :: Python :: 3.10
Classifier: Programming Language :: Python :: 3.11
Classifier: Programming Language :: Python :: 3.12
Requires-Python: >=3.10
Requires-Dist: polars>=1.24.0
Requires-Dist: polars-talib
Requires-Dist: numpy
Requires-Dist: rich
Requires-Dist: pyarrow
Requires-Dist: python-dateutil
